dumdum.py
dumdum-0.1.2.data/scripts/dumdum
dumdum-0.1.2.dist-info/DESCRIPTION.rst
dumdum-0.1.2.dist-info/METADATA
dumdum-0.1.2.dist-info/RECORD
dumdum-0.1.2.dist-info/WHEEL
dumdum-0.1.2.dist-info/metadata.json
dumdum-0.1.2.dist-info/top_level.txt
