Metadata-Version: 2.0
Name: dumdum
Version: 0.1.2
Summary: Easily create dummy HTTP servers
Home-page: http://www.github.com/jar-o/dumdum/
Author: James Robson
Author-email: dumdumpy@googlegroups.com
License: MIT
Platform: any
Classifier: Environment :: Web Environment
Classifier: Intended Audience :: Developers
Classifier: License :: OSI Approved :: BSD License
Classifier: Operating System :: OS Independent
Classifier: Programming Language :: Python
Classifier: Topic :: Internet :: WWW/HTTP :: Dynamic Content
Classifier: Topic :: Software Development :: Libraries :: Python Modules
Requires-Dist: pyparsing
